{"Name":"RustyMetalMaterial","SolidColorProperties":null,"TextureProperties":{"DiffuseTexturePath":"Material/RustyMetal/Diffuse","NormalTexturePath":"Material/RustyMetal/Normal","HeightTexturePath":"Material/RustyMetal/Height","RoughnessTexturePath":"Material/RustyMetal/Roughness","MetallicTexturePath":"Material/RustyMetal/Metallic","AmbientOcclusionTexturePath":"Material/RustyMetal/AO","EmissiveTexturePath":"Material/RustyMetal/Emissive","InvertNormalYAxis":true,"IsDepthMap":false,"ParallaxMinSteps":0,"ParallaxMaxSteps":0,"ParallaxHeightScale":0},"BaseReflectivity":0.04}